cryptobalancefinder/__init__.py
cryptobalancefinder/balance_checker.py
cryptobalancefinder/crypto_wallet.py
cryptobalancefinder/wallet_manager.py
cryptobalancefinder-1.0.2.dist-info/METADATA
cryptobalancefinder-1.0.2.dist-info/WHEEL
cryptobalancefinder-1.0.2.dist-info/entry_points.txt
cryptobalancefinder-1.0.2.dist-info/top_level.txt
cryptobalancefinder-1.0.2.dist-info/RECORD
