Metadata-Version: 2.1
Name: cryptobalancefinder
Version: 1.0.2
Summary: A tool for finding and checking cryptocurrency wallet balances from seed phrases
Home-page: https://github.com/yourusername/cryptobalancefinder
Author: CryptoBalanceFinder Team
Author-email: rbmorena42@gmail.com
Classifier: Development Status :: 3 - Alpha
Classifier: Intended Audience :: Developers
Classifier: License :: OSI Approved :: MIT License
Classifier: Operating System :: OS Independent
Classifier: Programming Language :: Python :: 3
Classifier: Programming Language :: Python :: 3.7
Classifier: Programming Language :: Python :: 3.8
Classifier: Programming Language :: Python :: 3.9
Classifier: Programming Language :: Python :: 3.10
Requires-Python: >=3.7
Requires-Dist: aiohttp>=3.8.0
Requires-Dist: pyyaml>=5.1
Requires-Dist: bip_utils>=2.9.3
Requires-Dist: argparse>=1.4.0
